h5pyd/__init__.py
h5pyd/config.py
h5pyd/h5ds.py
h5pyd/version.py
h5pyd/_apps/__init__.py
h5pyd/_apps/config.py
h5pyd/_apps/hsacl.py
h5pyd/_apps/hsconfigure.py
h5pyd/_apps/hscopy.py
h5pyd/_apps/hsdel.py
h5pyd/_apps/hsdiff.py
h5pyd/_apps/hsget.py
h5pyd/_apps/hsinfo.py
h5pyd/_apps/hsload.py
h5pyd/_apps/hsls.py
h5pyd/_apps/hsmv.py
h5pyd/_apps/hsstat.py
h5pyd/_apps/hstouch.py
h5pyd/_apps/utillib.py
h5pyd/_hl/__init__.py
h5pyd/_hl/attrs.py
h5pyd/_hl/base.py
h5pyd/_hl/dataset.py
h5pyd/_hl/datatype.py
h5pyd/_hl/dims.py
h5pyd/_hl/files.py
h5pyd/_hl/filters.py
h5pyd/_hl/folders.py
h5pyd/_hl/group.py
h5pyd/_hl/h5type.py
h5pyd/_hl/h5type_test.py
h5pyd/_hl/httpconn.py
h5pyd/_hl/objectid.py
h5pyd/_hl/openid.py
h5pyd/_hl/requests_lambda.py
h5pyd/_hl/selections.py
h5pyd/_hl/serverinfo.py
h5pyd/_hl/table.py
h5pyd-0.23.0.dist-info/licenses/COPYING
h5pyd-0.23.0.dist-info/METADATA
h5pyd-0.23.0.dist-info/WHEEL
h5pyd-0.23.0.dist-info/entry_points.txt
h5pyd-0.23.0.dist-info/top_level.txt
h5pyd-0.23.0.dist-info/RECORD
